llmfn.py
llmfn-0.1.0.dist-info/LICENSE
llmfn-0.1.0.dist-info/WHEEL
llmfn-0.1.0.dist-info/METADATA
llmfn-0.1.0.dist-info/RECORD
