Metadata-Version: 2.1
Name: llmfn
Version: 0.1.0
Summary: 
License: MIT
Author: IsaacBreen
Author-email: mail@isaacbreen.com
Requires-Python: >=3.9,<4.0
Classifier: License :: OSI Approved :: MIT License
Classifier: Programming Language :: Python :: 3
Classifier: Programming Language :: Python :: 3.9
Classifier: Programming Language :: Python :: 3.10
Classifier: Programming Language :: Python :: 3.11
Requires-Dist: openai (>=0.26.4,<0.27.0)
